MysqlHanshuDaquanCYuyanBianchengWang/README.md
MysqlHanshuDaquanCYuyanBianchengWang/__init__.py
MysqlHanshuDaquanCYuyanBianchengWang/__main__.py
MysqlHanshuDaquanCYuyanBianchengWang/file.epub
MysqlHanshuDaquanCYuyanBianchengWang/index.html
MysqlHanshuDaquanCYuyanBianchengWang/css/__init__.py
MysqlHanshuDaquanCYuyanBianchengWang/css/annotations.css
MysqlHanshuDaquanCYuyanBianchengWang/css/main.css
MysqlHanshuDaquanCYuyanBianchengWang/css/normalize.css
MysqlHanshuDaquanCYuyanBianchengWang/css/popup.css
MysqlHanshuDaquanCYuyanBianchengWang/font/__init__.py
MysqlHanshuDaquanCYuyanBianchengWang/font/fontello.eot
MysqlHanshuDaquanCYuyanBianchengWang/font/fontello.svg
MysqlHanshuDaquanCYuyanBianchengWang/font/fontello.ttf
MysqlHanshuDaquanCYuyanBianchengWang/font/fontello.woff
MysqlHanshuDaquanCYuyanBianchengWang/img/__init__.py
MysqlHanshuDaquanCYuyanBianchengWang/img/annotator-glyph-sprite.png
MysqlHanshuDaquanCYuyanBianchengWang/img/annotator-icon-sprite.png
MysqlHanshuDaquanCYuyanBianchengWang/img/apple-touch-icon.png
MysqlHanshuDaquanCYuyanBianchengWang/img/cancelfullscreen.png
MysqlHanshuDaquanCYuyanBianchengWang/img/close.png
MysqlHanshuDaquanCYuyanBianchengWang/img/fullscreen.png
MysqlHanshuDaquanCYuyanBianchengWang/img/loader.gif
MysqlHanshuDaquanCYuyanBianchengWang/img/menu-icon.png
MysqlHanshuDaquanCYuyanBianchengWang/img/save.png
MysqlHanshuDaquanCYuyanBianchengWang/img/saved.png
MysqlHanshuDaquanCYuyanBianchengWang/img/settings-s.png
MysqlHanshuDaquanCYuyanBianchengWang/img/settings.png
MysqlHanshuDaquanCYuyanBianchengWang/img/star.png
MysqlHanshuDaquanCYuyanBianchengWang/js/__init__.py
MysqlHanshuDaquanCYuyanBianchengWang/js/epub.js
MysqlHanshuDaquanCYuyanBianchengWang/js/epub.min.js
MysqlHanshuDaquanCYuyanBianchengWang/js/epub.min.map
MysqlHanshuDaquanCYuyanBianchengWang/js/hooks.min.js
MysqlHanshuDaquanCYuyanBianchengWang/js/hooks.min.map
MysqlHanshuDaquanCYuyanBianchengWang/js/reader.js
MysqlHanshuDaquanCYuyanBianchengWang/js/reader.js.map
mysql_hanshu_daquan_c_yuyan_biancheng_wang-2024.3.5.0.dist-info/METADATA
mysql_hanshu_daquan_c_yuyan_biancheng_wang-2024.3.5.0.dist-info/WHEEL
mysql_hanshu_daquan_c_yuyan_biancheng_wang-2024.3.5.0.dist-info/entry_points.txt
mysql_hanshu_daquan_c_yuyan_biancheng_wang-2024.3.5.0.dist-info/top_level.txt
mysql_hanshu_daquan_c_yuyan_biancheng_wang-2024.3.5.0.dist-info/RECORD
